{"partner_id": "ptr_R081", "address": "Cartagena de Indias, Colombia", "booking_link": "https://homeburgers.co", "category": "restaurant", "cuisine": "Hamburguesas", "description": "Hamburguesas premium con producto local. Una de las mejores cadenas del país.", "experience": "Cocina · Cócteles · Ambiente local", "image_url": "https://lh3.googleusercontent.com/place-photos/AJRVUZOxsTErghriwsXM2E_hXwqPrdeI153jBsESqh-6v95P_29MBHnaoJDAvfWO1y3IopxrMhJdyaLQgR_EjWiCLSn_-JWhBsxbMGP7kafT4rOv56H5KX9Q-tYTOad9bM7YW3THcoA0loo2as-I2XAeuq-RSw=s4800-w600", "instagram": "homeburgers", "is_certified": true, "location": {"lat": 10.422, "lng": -75.5482}, "name": "Home Burgers", "price_range": "$$", "rating": 4.5, "reviews": 920, "subcategory": "fastfood", "tier": "popular", "default_payment_link": "", "membership_paid_until": null, "membership_status": "active", "membership_tier": "popular", "membership_plan": "free", "phone": "+573114461111", "hours": "Lun-Dom 12:00 - 23:00"}