{"partner_id": "ptr_beauty_0422", "name": "Isabel Rojas peluquería y spa", "category": "beauty", "subcategory": "salon", "description": "Isabel Rojas peluquería y spa — servicios de belleza y cuidado personal en Cartagena.", "address": "Cra. 2 #4-115, Cartagena de Indias, Bolívar, Colombia", "location": {"lat": 10.399582100000002, "lng": -75.5592973}, "phone": "+573167509295", "image_url": "https://lh3.googleusercontent.com/place-photos/AJRVUZMCuGReS6h_wvgHbFyKkaE4nBpP2ul6W0EgtnAMxwsvFW69qimH1V4pNdTLECf5Yj4ocSkmJyjVTTHwLP0YKQvhJ1zpia89A96_DEH-MKk1yAA-u_LHQGyM4ppVdWDqy7F5vNG21AfbNMZ3qc4=s4800-w1200", "instagram": "", "booking_link": "https://book.weibook.co/isabel-rojas-peluqueria-y-spa", "rating": 4.9, "reviews": 93, "price_range": "$$", "tier": "standard", "hours": "Monday: 9:00 AM – 7:00 PM; Tuesday: 9:00 AM – 7:00 PM ...", "is_certified": false, "is_government": false, "experience": "", "default_payment_link": "", "membership_status": "inactive", "membership_tier": "standard", "membership_plan": "none", "membership_paid_until": null, "cuisine": ""}