{"partner_id":"ptr_X1189","address":"Islas del Rosario, Cartagena de Indias RNT, Cartagena de Indias, Bolívar, Colombia","booking_link":"http://www.coralinaisland.com/","category":"hotel","description":"Coralina Island — Top-rated hotel in Cartagena with 731 Google reviews.","experience":"Hotel · Cartagena","image_url":"/images/partners/ptr_X1189.jpg","instagram":"","is_certified":true,"location":{"lat":10.1766138,"lng":-75.75566839999999},"name":"Coralina Island","phone":"+573187772062","price_range":"$$","rating":4.5,"reviews":731,"subcategory":"boutique","tier":"popular","default_payment_link":"","membership_paid_until":null,"membership_status":"active","membership_tier":"popular","membership_plan":"free","hours":"Recepción 24h"}