{"partner_id":"ptr_R013","address":"Cartagena de Indias, Colombia","booking_link":"https://sanpasqual.co","category":"restaurant","cuisine":"Colombiano contemporáneo","description":"Cocina colombiana refinada con producto del Caribe. Patio colonial precioso.","experience":"Cocina · Cócteles · Ambiente local","image_url":"/images/partners/ptr_R013.jpg","instagram":"sanpasqualcartagena","is_certified":true,"location":{"lat":10.422,"lng":-75.5482},"name":"San Pasqual","price_range":"$$$","rating":4.6,"reviews":910,"subcategory":"colombian","tier":"premium","default_payment_link":"","membership_paid_until":null,"membership_status":"active","membership_tier":"premium","membership_plan":"free","phone":"+573159883201","hours":"Lun-Dom 12:00 - 23:00"}