{"partner_id":"ptr_R121","address":"Cartagena de Indias, Colombia","booking_link":"http://www.vedanacartagena.com/","category":"restaurant","cuisine":"Vegetariano · Vegano","description":"Cocina plant-based con menú creativo, bowls, smoothies y café.","experience":"Cocina · Cócteles · Ambiente local","image_url":"/images/partners/ptr_R121.jpg","instagram":"vedanacartagena","is_certified":true,"location":{"lat":10.422,"lng":-75.5482},"name":"Vedana","price_range":"$$","rating":4.6,"reviews":380,"subcategory":"vegetarian","tier":"popular","default_payment_link":"","membership_paid_until":null,"membership_status":"active","membership_tier":"popular","membership_plan":"free","phone":"+573133665723","hours":"Lun-Dom 12:00 - 23:00"}