{"partner_id":"ptr_1325","name":"Cafe San Antonio by Casa Jaguar","description":"","category":"restaurant","tier":"elite","image_url":"/images/partners/ptr_1325.jpg","location":{"lat":10.4199671,"lng":-75.54609889999999},"address":"Calle San Antonio, Cra. 10 #25-99, Getsemaní, Cartagena de Indias, Bolívar, Colombia","booking_link":"","price_range":"$$$","experience":"","is_certified":false,"instagram":"","subcategory":"restaurante","default_payment_link":"","membership_paid_until":null,"membership_status":"inactive","membership_tier":"free","membership_plan":null,"hours":null,"rating":4.8,"reviews":334,"phone":"","google_place_id":"ChIJmbXz8oEv9o4RlGDxuRgbN38"}